cmsnbiclient/E7/__init__.py
cmsnbiclient/E7/create.py
cmsnbiclient/E7/delete.py
cmsnbiclient/E7/query.py
cmsnbiclient/E7/update.py
cmsnbiclient/REST/__init__.py
cmsnbiclient/REST/query.py
cmsnbiclient/__init__.py
cmsnbiclient/__version__.py
cmsnbiclient/client.py
cmsnbiclient/client_v2.py
cmsnbiclient/core/__init__.py
cmsnbiclient/core/base.py
cmsnbiclient/core/circuit_breaker.py
cmsnbiclient/core/config.py
cmsnbiclient/core/logging.py
cmsnbiclient/core/transport.py
cmsnbiclient/monitoring/__init__.py
cmsnbiclient/security/__init__.py
cmsnbiclient/security/credentials.py
cmsnbiclient/security/xml.py
cms_nbi_client-2.0.0.dist-info/LICENSE
cms_nbi_client-2.0.0.dist-info/METADATA
cms_nbi_client-2.0.0.dist-info/WHEEL
cms_nbi_client-2.0.0.dist-info/RECORD
