Metadata-Version: 2.3
Name: cms-nbi-client
Version: 2.0.0
Summary: Modern async Python client for Calix Management System NBI
License: GPL-3.0
Author: somenetworking
Author-email: andrewshea06@gmail.com
Requires-Python: >=3.9,<4.0
Classifier: License :: OSI Approved :: GNU General Public License v3 (GPLv3)
Classifier: Programming Language :: Python :: 3
Classifier: Programming Language :: Python :: 3.9
Classifier: Programming Language :: Python :: 3.10
Classifier: Programming Language :: Python :: 3.11
Classifier: Programming Language :: Python :: 3.12
Classifier: Programming Language :: Python :: 3.13
Requires-Dist: aiocache (>=0.12.0,<0.13.0)
Requires-Dist: aiohttp (>=3.9.0,<4.0.0)
Requires-Dist: cryptography (>=41.0.0,<42.0.0)
Requires-Dist: defusedxml (>=0.7.1,<0.8.0)
Requires-Dist: opentelemetry-api (>=1.21.0,<2.0.0)
Requires-Dist: opentelemetry-sdk (>=1.21.0,<2.0.0)
Requires-Dist: prometheus-client (>=0.19.0,<0.20.0)
Requires-Dist: pydantic (>=2.5.0,<3.0.0)
Requires-Dist: python-keyring (>=24.3.0,<25.0.0)
Requires-Dist: structlog (>=23.2.0,<24.0.0)
Requires-Dist: tenacity (>=8.2.0,<9.0.0)
Requires-Dist: xmltodict (>=0.13.0,<0.14.0)
